SpectDetect/SpectDetect.py
SpectDetect/__init__.py
SpectDetect-0.0.4.dist-info/LICENSE
SpectDetect-0.0.4.dist-info/METADATA
SpectDetect-0.0.4.dist-info/WHEEL
SpectDetect-0.0.4.dist-info/top_level.txt
SpectDetect-0.0.4.dist-info/RECORD
